yandex_cloud_ml_sdk/__init__.py
yandex_cloud_ml_sdk/_auth.py
yandex_cloud_ml_sdk/_authorization.py
yandex_cloud_ml_sdk/_client.py
yandex_cloud_ml_sdk/_exceptions.py
yandex_cloud_ml_sdk/_logging.py
yandex_cloud_ml_sdk/_retry.py
yandex_cloud_ml_sdk/_sdk.py
yandex_cloud_ml_sdk/assistants.py
yandex_cloud_ml_sdk/auth.py
yandex_cloud_ml_sdk/exceptions.py
yandex_cloud_ml_sdk/py.typed
yandex_cloud_ml_sdk/retry.py
yandex_cloud_ml_sdk/search_api.py
yandex_cloud_ml_sdk/search_indexes.py
yandex_cloud_ml_sdk/_assistants/__init__.py
yandex_cloud_ml_sdk/_assistants/assistant.py
yandex_cloud_ml_sdk/_assistants/domain.py
yandex_cloud_ml_sdk/_assistants/prompt_truncation_options.py
yandex_cloud_ml_sdk/_assistants/utils.py
yandex_cloud_ml_sdk/_batch/__init__.py
yandex_cloud_ml_sdk/_batch/domain.py
yandex_cloud_ml_sdk/_chat/__init__.py
yandex_cloud_ml_sdk/_chat/base_function.py
yandex_cloud_ml_sdk/_chat/completions/__init__.py
yandex_cloud_ml_sdk/_chat/completions/config.py
yandex_cloud_ml_sdk/_chat/completions/function.py
yandex_cloud_ml_sdk/_chat/completions/message.py
yandex_cloud_ml_sdk/_chat/completions/model.py
yandex_cloud_ml_sdk/_chat/completions/result.py
yandex_cloud_ml_sdk/_chat/completions/utils.py
yandex_cloud_ml_sdk/_chat/text_embeddings/__init__.py
yandex_cloud_ml_sdk/_chat/text_embeddings/config.py
yandex_cloud_ml_sdk/_chat/text_embeddings/function.py
yandex_cloud_ml_sdk/_chat/text_embeddings/model.py
yandex_cloud_ml_sdk/_chat/text_embeddings/result.py
yandex_cloud_ml_sdk/_datasets/__init__.py
yandex_cloud_ml_sdk/_datasets/dataset.py
yandex_cloud_ml_sdk/_datasets/domain.py
yandex_cloud_ml_sdk/_datasets/draft.py
yandex_cloud_ml_sdk/_datasets/schema.py
yandex_cloud_ml_sdk/_datasets/status.py
yandex_cloud_ml_sdk/_datasets/task_types.py
yandex_cloud_ml_sdk/_datasets/uploaders.py
yandex_cloud_ml_sdk/_datasets/validation.py
yandex_cloud_ml_sdk/_experimental/__init__.py
yandex_cloud_ml_sdk/_experimental/audio/__init__.py
yandex_cloud_ml_sdk/_experimental/audio/microphone.py
yandex_cloud_ml_sdk-0.17.1.dist-info/LICENSE
yandex_cloud_ml_sdk-0.17.1.dist-info/WHEEL
yandex_cloud_ml_sdk-0.17.1.dist-info/METADATA
yandex_cloud_ml_sdk-0.17.1.dist-info/RECORD
