Metadata-Version: 2.1
Name: yandex-cloud-ml-sdk
Version: 0.17.1
Summary: Multimodal SDK for working with Yandex Cloud ML services
Author-email: Vladimir Lipkin <lipkin@yandex-team.ru>
Requires-Python: >=3.9
Classifier: Typing :: Typed
Classifier: Development Status :: 3 - Alpha
Classifier: Intended Audience :: Developers
Classifier: Intended Audience :: Science/Research
Classifier: License :: OSI Approved :: Apache Software License
Classifier: Programming Language :: Python :: 3 :: Only
Classifier: Programming Language :: Python :: 3.9
Classifier: Programming Language :: Python :: 3.10
Classifier: Programming Language :: Python :: 3.11
Classifier: Programming Language :: Python :: 3.12
Classifier: Programming Language :: Python :: 3.13
Classifier: Operating System :: OS Independent
Classifier: Operating System :: POSIX
Classifier: Operating System :: MacOS
Classifier: Operating System :: POSIX :: Linux
Classifier: Operating System :: Microsoft :: Windows
Classifier: Topic :: Software Development :: Libraries :: Python Modules
Classifier: Topic :: Scientific/Engineering :: Artificial Intelligence
Requires-Dist: yandexcloud>=0.359.0
Requires-Dist: grpcio>=1.70.0
Requires-Dist: get-annotations
Requires-Dist: httpx>=0.27,<1
Requires-Dist: httpx-sse>=0.4.1
Requires-Dist: typing-extensions>=4
Requires-Dist: aiofiles>=24.1.0
Requires-Dist: packaging>=24
Requires-Dist: pyarrow>=19 ; extra == "datasets"
Requires-Dist: langchain-core>=0.3 ; extra == "langchain"
Requires-Dist: pydantic<2.10 ; extra == "langchain"
Requires-Dist: pydantic>2 ; extra == "pydantic"
Requires-Dist: pre-commit ; extra == "test"
Requires-Dist: tox ; extra == "test"
Project-URL: Documentation, https://yandex.cloud/ru/docs/foundation-models/
Project-URL: Source, https://github.com/yandex-cloud/yandex-cloud-ml-sdk
Project-URL: Tracker, https://github.com/yandex-cloud/yandex-cloud-ml-sdk/issues
Provides-Extra: datasets
Provides-Extra: langchain
Provides-Extra: pydantic
Provides-Extra: test
